_libparse.cpython-311-darwin.so
libparse/__init__.py
libparse/__version__.py
libparse/__main__.py
lln_libparse-0.56.0.dist-info/RECORD
lln_libparse-0.56.0.dist-info/WHEEL
lln_libparse-0.56.0.dist-info/top_level.txt
lln_libparse-0.56.0.dist-info/METADATA
