Metadata-Version: 2.1
Name: lln-libparse
Version: 0.56.0
Summary: Python wrapper around Yosys' libparse module
Author: Mohamed Gaber
Author-email: me@donn.website
Requires-Python: >=3.8
Requires-Dist: wheel
